odoo/addons/stock_weighing/README.rst
odoo/addons/stock_weighing/__init__.py
odoo/addons/stock_weighing/__manifest__.py
odoo/addons/stock_weighing/init_hook.py
odoo/addons/stock_weighing/controllers/__init__.py
odoo/addons/stock_weighing/controllers/start_screen.py
odoo/addons/stock_weighing/demo/picking_type_demo.xml
odoo/addons/stock_weighing/demo/weight_label_demo.xml
odoo/addons/stock_weighing/i18n/ca.po
odoo/addons/stock_weighing/i18n/es.po
odoo/addons/stock_weighing/i18n/stock_weighing.pot
odoo/addons/stock_weighing/models/__init__.py
odoo/addons/stock_weighing/models/stock_move.py
odoo/addons/stock_weighing/models/stock_move_line.py
odoo/addons/stock_weighing/models/stock_picking.py
odoo/addons/stock_weighing/models/stock_picking_type.py
odoo/addons/stock_weighing/models/weighing_mixin.py
odoo/addons/stock_weighing/readme/CONFIGURE.md
odoo/addons/stock_weighing/readme/CONTEXT.md
odoo/addons/stock_weighing/readme/CONTRIBUTORS.md
odoo/addons/stock_weighing/readme/DESCRIPTION.md
odoo/addons/stock_weighing/readme/ROADMAP.md
odoo/addons/stock_weighing/readme/USAGE.md
odoo/addons/stock_weighing/security/ir.model.access.csv
odoo/addons/stock_weighing/static/description/icon.png
odoo/addons/stock_weighing/static/description/icon.svg
odoo/addons/stock_weighing/static/description/index.html
odoo/addons/stock_weighing/static/src/base_weight_record_form/base_weight_record_form.esm.js
odoo/addons/stock_weighing/static/src/base_weight_record_form/base_weight_record_form.xml
odoo/addons/stock_weighing/static/src/base_weight_record_kanban/base_weight_record_kanban.esm.js
odoo/addons/stock_weighing/static/src/base_weight_record_kanban/base_weight_record_kanban.scss
odoo/addons/stock_weighing/static/src/base_weight_record_kanban/base_weight_record_kanban.xml
odoo/addons/stock_weighing/static/src/weight_recording_form/weight_recording_form.esm.js
odoo/addons/stock_weighing/views/start_screen_banner.xml
odoo/addons/stock_weighing/views/stock_move_line_views.xml
odoo_addon_stock_weighing-15.0.2.3.0.3.dist-info/METADATA
odoo_addon_stock_weighing-15.0.2.3.0.3.dist-info/WHEEL
odoo_addon_stock_weighing-15.0.2.3.0.3.dist-info/top_level.txt
odoo_addon_stock_weighing-15.0.2.3.0.3.dist-info/RECORD
