Metadata-Version: 2.1
Name: odoo-addon-stock_weighing
Version: 15.0.2.3.0.3
Summary: Weighing assistant for stock operations
Home-page: https://github.com/OCA/stock-weighing
Author: Tecnativa, Odoo Community Association (OCA)
Author-email: support@odoo-community.org
License: AGPL-3
Classifier: Programming Language :: Python
Classifier: Framework :: Odoo
Classifier: Framework :: Odoo :: 15.0
Classifier: License :: OSI Approved :: GNU Affero General Public License v3
Requires-Python: >=3.8
Requires-Dist: odoo-addon-web-filter-header-button<15.1dev,>=15.0dev
Requires-Dist: odoo-addon-web-ir-actions-act-multi<15.1dev,>=15.0dev
Requires-Dist: odoo-addon-web-widget-numeric-step<15.1dev,>=15.0dev
Requires-Dist: odoo<15.1dev,>=15.0a
